fgclustering/__init__.py
fgclustering/_version.py
fgclustering/clustering.py
fgclustering/distance.py
fgclustering/forest_guided_clustering.py
fgclustering/optimizer.py
fgclustering/plotting.py
fgclustering/statistics.py
fgclustering/utils.py
fgclustering-2.0.2.dist-info/licenses/LICENSE
fgclustering-2.0.2.dist-info/METADATA
fgclustering-2.0.2.dist-info/WHEEL
fgclustering-2.0.2.dist-info/top_level.txt
fgclustering-2.0.2.dist-info/RECORD
