Metadata-Version: 2.4
Name: fgclustering
Version: 2.0.2
Summary: Forest-Guided Clustering - Explainability method for Random Forest models.
Author: Dominik Thalmeier, Helena Pelin
Author-email: Lisa Barros de Andrade e Sousa <lisa.barros.andrade.sousa@gmail.com>, Marie Piraud <marie.piraud@helmholtz-muenchen.de>
Maintainer-email: Lisa Barros de Andrade e Sousa <lisa.barros.andrade.sousa@gmail.com>
Project-URL: documentation, https://forest-guided-clustering.readthedocs.io/en/latest/
Project-URL: repository, https://github.com/HelmholtzAI-Consultants-Munich/fg-clustering
Keywords: random forest,xai,explainable ai
Classifier: Programming Language :: Python :: 3
Classifier: License :: OSI Approved :: MIT License
Classifier: Operating System :: OS Independent
Requires-Python: >=3.7
License-File: LICENSE
Requires-Dist: pandas
Requires-Dist: numpy
Requires-Dist: matplotlib
Requires-Dist: seaborn>=0.12
Requires-Dist: scikit-learn
Requires-Dist: kmedoids
Requires-Dist: scipy
Requires-Dist: tqdm
Requires-Dist: statsmodels>=0.13.5
Requires-Dist: numexpr>=2.8.4
Requires-Dist: numba
Requires-Dist: imblearn
Requires-Dist: plotly
Requires-Dist: nbformat
Provides-Extra: dev
Requires-Dist: pytest; extra == "dev"
Dynamic: license-file
